maesters/__init__.py
maesters/citadels/__init__.py
maesters/citadels/CMC/__init__.py
maesters/citadels/CMC/gem.py
maesters/citadels/CMC/geps_ens.py
maesters/citadels/DWD/__init__.py
maesters/citadels/DWD/icon.py
maesters/citadels/ECMWF/__init__.py
maesters/citadels/ECMWF/enfo.py
maesters/citadels/ECMWF/oper.py
maesters/config/__init__.py
maesters/config/cmc.toml
maesters/config/dwd.toml
maesters/config/ecmwf.toml
maesters/config/gfs.toml
maesters/config/models.toml
maesters/static/pf_split
maesters/static/dwd/target_grid_world_0125.txt
maesters/static/dwd/weights_icogl2world_0125.nc
maesters/utils/__init__.py
maesters/utils/download.py
maesters/utils/post_process.py
maesters_nwp-0.0.9.dist-info/LICENSE
maesters_nwp-0.0.9.dist-info/METADATA
maesters_nwp-0.0.9.dist-info/WHEEL
maesters_nwp-0.0.9.dist-info/top_level.txt
maesters_nwp-0.0.9.dist-info/RECORD
