Metadata-Version: 2.1
Name: maesters-nwp
Version: 0.0.9
Summary: A package to get open NWP data in a elegant way
Home-page: https://github.com/cnmetlab/Maesters-of-NWP
Author: blizhan
Author-email: blizhan@icloud.com
Classifier: Programming Language :: Python :: 3
Requires-Python: >=3.7
License-File: LICENSE
Requires-Dist: retrying
Requires-Dist: beautifulsoup4
Requires-Dist: pygrib
Requires-Dist: netCDF4
Requires-Dist: xarray
Requires-Dist: requests
Requires-Dist: loguru
Requires-Dist: toml
Requires-Dist: dask
